fastahold/__init__.py
fastahold/core/__init__.py
fastahold/tests/__init__.py
fastahold/tests/test_1984.py
fastahold-0.0.1.dev0.dist-info/LICENSE.txt
fastahold-0.0.1.dev0.dist-info/METADATA
fastahold-0.0.1.dev0.dist-info/WHEEL
fastahold-0.0.1.dev0.dist-info/top_level.txt
fastahold-0.0.1.dev0.dist-info/RECORD
