Metadata-Version: 2.2
Name: fastahold
Version: 0.0.1.dev0
Summary: This project provides classes for the storing of FASTA data.
Author-email: Johannes <johannes-programming@mailfence.com>
License: The MIT License (MIT)
Project-URL: Download, https://pypi.org/project/fastahold/#files
Project-URL: Index, https://pypi.org/project/fastahold/
Project-URL: Source, https://github.com/johannes-programming/fastahold/
Project-URL: Website, https://fastahold.johannes-programming.online/
Classifier: Development Status :: 2 - Pre-Alpha
Classifier: License :: OSI Approved :: MIT License
Classifier: Natural Language :: English
Classifier: Operating System :: OS Independent
Classifier: Programming Language :: Python
Classifier: Programming Language :: Python :: 3
Classifier: Programming Language :: Python :: 3 :: Only
Classifier: Typing :: Typed
Requires-Python: >=3.8
License-File: LICENSE.txt
Requires-Dist: Bio>=1.7.1
